routeuuid/__init__.py
routeuuid/converters.py
routeuuid-0.1.0.dist-info/licenses/LICENSE
routeuuid-0.1.0.dist-info/METADATA
routeuuid-0.1.0.dist-info/WHEEL
routeuuid-0.1.0.dist-info/top_level.txt
routeuuid-0.1.0.dist-info/RECORD
