Metadata-Version: 2.4
Name: routeuuid
Version: 0.1.0
Summary: A Flask extension that provides UUID converters for different UUID versions.
Author-email: C-Ewan <ewan.debug@gmail.com>
License: MIT License
Project-URL: Homepage, https://github.com/C-Ewan/routeuuid
Project-URL: Documentation, https://github.com/C-Ewan/routeuuid#readme
Project-URL: Repository, https://github.com/C-Ewan/routeuuid
Project-URL: Issue Tracker, https://github.com/C-Ewan/routeuuid/issues
Classifier: Programming Language :: Python :: 3
Classifier: License :: OSI Approved :: MIT License
Classifier: Operating System :: OS Independent
Classifier: Environment :: Web Environment
Classifier: Intended Audience :: Developers
Classifier: Topic :: Internet :: WWW/HTTP :: WSGI
Classifier: Topic :: Software Development :: Libraries :: Python Modules
Classifier: Framework :: Flask
Requires-Python: >=3.13.3
License-File: LICENSE
Requires-Dist: Flask>=3.1.1
Requires-Dist: Werkzeug>=3.1.3
Dynamic: license-file
